wkeMiniblink/__init__.py
wkeMiniblink/miniblink.py
wkeMiniblink/wke.py
wkeMiniblink/wkeEvent.py
wkeMiniblink/wkeStruct.py
wkeMiniblink/wkeWin32.py
wkeMiniblink/wkeWin32ProcMsg.py
wkeMiniblink/__pyinstaller/__init__.py
wkeMiniblink/__pyinstaller/hook-wkeMiniblink.py
wkeMiniblink/bin/miniblink_4975_x32.dll
wkeMiniblink/bin/miniblink_4975_x64.dll
wkeMiniblink/bin/npswf32-11.5.dll
wkeminiblink-0.1.17.dist-info/LICENSE
wkeminiblink-0.1.17.dist-info/METADATA
wkeminiblink-0.1.17.dist-info/WHEEL
wkeminiblink-0.1.17.dist-info/entry_points.txt
wkeminiblink-0.1.17.dist-info/top_level.txt
wkeminiblink-0.1.17.dist-info/RECORD
