Metadata-Version: 2.1
Name: wkeminiblink
Version: 0.1.17
Summary: A python binding of Miniblink
Author: StoneFlaw
Author-email: wyh917@163.com
Project-URL: Documentation, https://pywkeminiblink.readthedocs.io/zh-cn/latest/
Project-URL: Source Code, https://github.com/StoneFlaw/PyWkeMiniblink
Project-URL: Bug Tracker, https://github.com/StoneFlaw/PyWkeMiniblink/issues
Project-URL: Homepage, https://pypi.org/project/WkeMiniblink/
Keywords: Miniblink Wke webbrowser
Classifier: Programming Language :: Python :: 3
Classifier: License :: OSI Approved :: GNU General Public License v3 (GPLv3)
Classifier: Operating System :: Microsoft :: Windows
License-File: LICENSE
Requires-Dist: Pywin32
Provides-Extra: docs
Requires-Dist: sphinx; extra == "docs"
Requires-Dist: sphinx-rtd-theme; extra == "docs"
